LICENSE.txt
README.md
setup.cfg
setup.py
msgtools/__init__.py
msgtools.egg-info/PKG-INFO
msgtools.egg-info/SOURCES.txt
msgtools.egg-info/dependency_links.txt
msgtools.egg-info/entry_points.txt
msgtools.egg-info/not-zip-safe
msgtools.egg-info/requires.txt
msgtools.egg-info/top_level.txt
msgtools/console/__init__.py
msgtools/console/client.py
msgtools/console/config_settings.py
msgtools/console/console.py
msgtools/console/server.py
msgtools/csvparse/__init__.py
msgtools/csvparse/csvparse.py
msgtools/database/__init__.py
msgtools/database/dalmatiner.py
msgtools/database/db_msgserver_plugin.py
msgtools/database/influx.png
msgtools/database/influxdb.py
msgtools/database/questdb.py
msgtools/debug/__init__.py
msgtools/debug/debug.png
msgtools/debug/debug.py
msgtools/debug/findprints.py
msgtools/debug/launcher.py
msgtools/inspector/__init__.py
msgtools/inspector/inspector.png
msgtools/inspector/inspector.py
msgtools/inspector/launcher.py
msgtools/launcher/__init__.py
msgtools/launcher/codegen_gui.py
msgtools/launcher/launcher.png
msgtools/launcher/launcher.py
msgtools/lib/__init__.py
msgtools/lib/app.py
msgtools/lib/client_connection.py
msgtools/lib/conversions.py
msgtools/lib/createmsgdialog.py
msgtools/lib/file_reader.py
msgtools/lib/gui.py
msgtools/lib/header_translator.py
msgtools/lib/message.py
msgtools/lib/messaging.py
msgtools/lib/msgcsv.py
msgtools/lib/msgjson.py
msgtools/lib/msgpandas.py
msgtools/lib/msgplot.py
msgtools/lib/txtreewidget.py
msgtools/lib/unknownmsg.py
msgtools/lumberjack/__init__.py
msgtools/lumberjack/lumberjack.py
msgtools/lumberjack/read_json.py
msgtools/multilog/__init__.py
msgtools/multilog/multilog.py
msgtools/noisemaker/__init__.py
msgtools/noisemaker/bandwidthtestecho.py
msgtools/noisemaker/bandwidthtester.py
msgtools/noisemaker/launcher.py
msgtools/noisemaker/noisemaker.png
msgtools/noisemaker/noisemaker.py
msgtools/parser/MsgUtils.py
msgtools/parser/__init__.py
msgtools/parser/check.py
msgtools/parser/parser.py
msgtools/parser/c/HeaderTemplate.h
msgtools/parser/c/Template.h
msgtools/parser/c/__init__.py
msgtools/parser/c/language.py
msgtools/parser/cosmos/HeaderTemplate.txt
msgtools/parser/cosmos/Template.txt
msgtools/parser/cosmos/__init__.py
