Metadata-Version: 2.1
Name: msgtools
Version: 0.40.10
Summary: Tools for fixed binary protocols
Home-page: https://github.com/MilesEngineering/MsgTools/
Author: Miles Gazic
Author-email: miles.gazic@gmail.com
License: LGPLv2
Project-URL: Documentation, https://github.com/MilesEngineering/MsgTools/wiki
Project-URL: Source, https://github.com/MilesEngineering/MsgTools/
Project-URL: Tracker, https://github.com/MilesEngineering/MsgTools/issues
Keywords: development tools messaging messages message generator protocol networking
Classifier: Intended Audience :: Developers
Classifier: Programming Language :: Python :: 3
Classifier: Topic :: Software Development :: Code Generators
Classifier: Topic :: Software Development :: Embedded Systems
Classifier: Topic :: Utilities
Requires-Python: >=3.5
Provides-Extra: gui
Provides-Extra: influxdb
Provides-Extra: questdb
License-File: LICENSE.txt
